paranet/__init__.py
paranet/__main__.py
paranet/models.py
paranet/utils.py
paranet/multivariate/__init__.py
paranet/multivariate/dists.py
paranet/multivariate/gradient.py
paranet/multivariate/multi_utils.py
paranet/univariate/__init__.py
paranet/univariate/dists.py
paranet/univariate/gradient.py
paranet/univariate/solvers_grad.py
paranet-0.1.4.dist-info/LICENSE.txt
paranet-0.1.4.dist-info/METADATA
paranet-0.1.4.dist-info/WHEEL
paranet-0.1.4.dist-info/top_level.txt
paranet-0.1.4.dist-info/RECORD
