Metadata-Version: 2.1
Name: paranet
Version: 0.1.4
Summary: paranet package
Home-page: https://github.com/ErikinBC/paranet
Author: Erik Drysdale
Author-email: erikinwest@gmail.com
License: GPLv3
Classifier: Development Status :: 3 - Alpha
Classifier: Intended Audience :: Science/Research
Classifier: License :: OSI Approved :: GNU General Public License v3 (GPLv3)
Classifier: Operating System :: POSIX :: Linux
Classifier: Programming Language :: Python :: 3
Requires-Dist: numpy
Requires-Dist: pandas
Requires-Dist: scipy
